__init__.py
dataflow_trigger.py
deferrable_dataflow_operator.py
custom_deferrable_dataflow_operator-1.0.0.dist-info/LICENSE.txt
custom_deferrable_dataflow_operator-1.0.0.dist-info/METADATA
custom_deferrable_dataflow_operator-1.0.0.dist-info/WHEEL
custom_deferrable_dataflow_operator-1.0.0.dist-info/top_level.txt
custom_deferrable_dataflow_operator-1.0.0.dist-info/RECORD
