Metadata-Version: 2.1
Name: custom-deferrable-dataflow-operator
Version: 1.0.0
Summary: Start your Dataflow jobs execution directly from the Triggerer without going to the Worker.
Home-page: https://github.com/AlvaroCavalcante/airflow-custom-deferrable-dataflow-operator
Author: Alvaro Leandro Cavalcante Carneiro
Author-email: alvaroleandro250@gmail.com
License: Apache License 2.0
Download-URL: https://github.com/AlvaroCavalcante/airflow-custom-deferrable-dataflow-operator
Keywords: airflow,apache-airflow,python,python3,dataflow,gcp,cloud-composer,google-cloud,dag,benchmark,apache,data,data-engineering
Platform: UNKNOWN
Classifier: Programming Language :: Python
Classifier: Programming Language :: Python :: 3
Classifier: Natural Language :: English
Classifier: Operating System :: OS Independent
Classifier: Intended Audience :: Developers
Classifier: Intended Audience :: Information Technology
Classifier: Development Status :: 4 - Beta
Classifier: License :: OSI Approved :: Apache Software License
Classifier: Topic :: Software Development :: Libraries :: Python Modules
Classifier: Framework :: Apache Airflow
Requires-Python: >=3.8
License-File: LICENSE.txt
Requires-Dist: apache-airflow>=2.10.0
Requires-Dist: google-cloud>=0.33.0
